Metadata-Version: 2.1
Name: simple_emulator
Version: 0.1.0
Summary: The competition system for MMGC 2021
Home-page: https://github.com/AItransCompetition/simple_emulator/tree/mmgc
Author: MMGC 2021
Author-email: 240326315@qq.com
License: UNKNOWN
Platform: UNKNOWN
Classifier: Programming Language :: Python :: 3
Classifier: License :: OSI Approved :: MIT License
Classifier: Operating System :: OS Independent
Requires-Python: >=3.0
